symcollab/rewrite/__init__.py
symcollab/rewrite/forward_closure.py
symcollab/rewrite/rule.py
symcollab/rewrite/system.py
symcollab/rewrite/variants.py
symcollab_rewrite-0.1.1.dist-info/METADATA
symcollab_rewrite-0.1.1.dist-info/WHEEL
symcollab_rewrite-0.1.1.dist-info/top_level.txt
symcollab_rewrite-0.1.1.dist-info/RECORD
